zmapio/__init__.py
zmapio/__version__.py
zmapio/reader.py
zmapio/writer.py
zmapio/zmap.py
zmapio-0.8.1.dist-info/LICENSE
zmapio-0.8.1.dist-info/METADATA
zmapio-0.8.1.dist-info/WHEEL
zmapio-0.8.1.dist-info/top_level.txt
zmapio-0.8.1.dist-info/RECORD
