Metadata-Version: 2.1
Name: zmapio
Version: 0.8.1
Summary: Python library for reading and writing map gridded data using ZMAP Plus ASCII Grid format
Home-page: https://github.com/abduhbm/zmapio
Author: Abdulelah Bin Mahfoodh
License: MIT
Keywords: ZMAP Plus Grid format
Classifier: Development Status :: 3 - Alpha
Classifier: License :: OSI Approved :: MIT License
Classifier: Programming Language :: Python
Classifier: Programming Language :: Python :: 3
Classifier: Programming Language :: Python :: 3.6
Classifier: Programming Language :: Python :: 3.7
Classifier: Programming Language :: Python :: 3.8
Classifier: Topic :: Utilities
Classifier: Topic :: Scientific/Engineering :: GIS
Classifier: Topic :: Scientific/Engineering :: Visualization
Provides-Extra: all
Provides-Extra: test
License-File: LICENSE
